parareal/__init__.py
parareal/abstract.py
parareal/forward_euler.py
parareal/futures.py
parareal/harmonic_oscillator.py
parareal/iterate_solution.py
parareal/parareal.py
parareal/py.typed
parareal/tabulate_solution.py
parareal-0.1.0.dist-info/LICENSE
parareal-0.1.0.dist-info/WHEEL
parareal-0.1.0.dist-info/METADATA
parareal-0.1.0.dist-info/RECORD
